.travis.yml
LICENSE
MANIFEST.in
README.rst
setup.cfg
setup.py
tox.ini
Mopidy_GPIO420.egg-info/PKG-INFO
Mopidy_GPIO420.egg-info/SOURCES.txt
Mopidy_GPIO420.egg-info/dependency_links.txt
Mopidy_GPIO420.egg-info/entry_points.txt
Mopidy_GPIO420.egg-info/not-zip-safe
Mopidy_GPIO420.egg-info/requires.txt
Mopidy_GPIO420.egg-info/top_level.txt
mopidy_gpio420/__init__.py
mopidy_gpio420/ext.conf
mopidy_gpio420/frontend.py