Metadata-Version: 1.1
Name: Mopidy-GPIO420
Version: 0.1.0
Summary: Extension to control mopidy with gpio buttons and display things on 16x2 lcd
Home-page: https://github.com/v1nc/mopidy-gpio420
Author: v1nc
Author-email: reckendreesv@gmail.com
License: Apache License, Version 2.0
Platform: UNKNOWN
Classifier: Environment :: No Input/Output (Daemon)
Classifier: Intended Audience :: End Users/Desktop
Classifier: License :: OSI Approved :: Apache Software License
Classifier: Operating System :: OS Independent
Classifier: Programming Language :: Python :: 2
Classifier: Topic :: Multimedia :: Sound/Audio :: Players
